{
  "window":{
    "width":368,
    "height":270
  },
  "camera":{
    "x":705.0,
    "y":269.0,
    "zoom":0.15184320860152034,
    "rotation":0.0,
    "margin":80.0
  },
  "rays":1840,
  "objects":[
    {
      "type":"polygon",
      "x":746.14021517472565,
      "y":-296.1486888706321,
      "scale":8.2545222106991822,
      "rotation":1.0176508101880763,
      "texture":"",
      "color":16777215,
      "opacity":1.0,
      "reflectivity":0.34999999999999998,
      "roughness":0.65000000000000002,
      "textureId":0,
      "materialId":1,
      "numPoints":4,
      "baseShapePoints":[
        {
          "x":-25.0,
          "y":-25.0
        },
        {
          "x":25.0,
          "y":-25.0
        },
        {
          "x":25.0,
          "y":25.0
        },
        {
          "x":-25.0,
          "y":25.0
        }
      ]
    },
    {
      "type":"polygon",
      "x":83.636048231875066,
      "y":760.54711798765402,
      "scale":6.4728172614465329,
      "rotation":-0.52706293007448324,
      "texture":"",
      "color":16777215,
      "opacity":1.0,
      "reflectivity":0.34999999999999998,
      "roughness":0.65000000000000002,
      "textureId":0,
      "materialId":1,
      "numPoints":4,
      "baseShapePoints":[
        {
          "x":-25.0,
          "y":-25.0
        },
        {
          "x":25.0,
          "y":-25.0
        },
        {
          "x":25.0,
          "y":25.0
        },
        {
          "x":-25.0,
          "y":25.0
        }
      ]
    },
    {
      "type":"polygon",
      "x":1383.5212882402461,
      "y":-70.523540322322276,
      "scale":3.7482982415870802,
      "rotation":0.46632035734592353,
      "texture":"",
      "color":16777215,
      "opacity":1.0,
      "reflectivity":0.34999999999999998,
      "roughness":0.65000000000000002,
      "textureId":0,
      "materialId":1,
      "numPoints":4,
      "baseShapePoints":[
        {
          "x":-25.0,
          "y":-25.0
        },
        {
          "x":25.0,
          "y":-25.0
        },
        {
          "x":25.0,
          "y":25.0
        },
        {
          "x":-25.0,
          "y":25.0
        }
      ]
    },
    {
      "type":"polygon",
      "x":-189.07274094131321,
      "y":327.36005552592439,
      "scale":5.9136791000122759,
      "rotation":0.63303185820339536,
      "texture":"",
      "color":16777215,
      "opacity":1.0,
      "reflectivity":0.34999999999999998,
      "roughness":0.65000000000000002,
      "textureId":0,
      "materialId":1,
      "numPoints":4,
      "baseShapePoints":[
        {
          "x":-25.0,
          "y":-25.0
        },
        {
          "x":25.0,
          "y":-25.0
        },
        {
          "x":25.0,
          "y":25.0
        },
        {
          "x":-25.0,
          "y":25.0
        }
      ]
    },
    {
      "type":"polygon",
      "x":1006.6615331754351,
      "y":291.57530926501067,
      "scale":3.2926159318180868,
      "rotation":0.11229320203597243,
      "texture":"",
      "color":16777215,
      "opacity":1.0,
      "reflectivity":0.34999999999999998,
      "roughness":0.65000000000000002,
      "textureId":0,
      "materialId":1,
      "numPoints":4,
      "baseShapePoints":[
        {
          "x":-25.0,
          "y":-25.0
        },
        {
          "x":25.0,
          "y":-25.0
        },
        {
          "x":25.0,
          "y":25.0
        },
        {
          "x":-25.0,
          "y":25.0
        }
      ]
    }
  ],
  "path":{
    "mode":"BEZIER_CUBIC",
    "points":[
      {
        "x":261,
        "y":8,
        "rotation":0.0,
        "handleLink":false,
        "velocity1":{
          "vx":160,
          "vy":-44
        }
      },
      {
        "x":673,
        "y":362,
        "rotation":0.0,
        "handleLink":false,
        "velocity1":{
          "vx":-178,
          "vy":-2
        },
        "velocity2":{
          "vx":178,
          "vy":2
        }
      },
      {
        "x":1027,
        "y":110,
        "rotation":0.0,
        "handleLink":false,
        "velocity1":{
          "vx":182,
          "vy":8
        },
        "velocity2":{
          "vx":-182,
          "vy":-8
        }
      },
      {
        "x":817,
        "y":654,
        "rotation":0.0,
        "handleLink":false,
        "velocity1":{
          "vx":-177,
          "vy":8
        },
        "velocity2":{
          "vx":177,
          "vy":-8
        }
      },
      {
        "x":313,
        "y":585,
        "rotation":0.0,
        "handleLink":false,
        "velocity1":{
          "vx":-63,
          "vy":-173
        },
        "velocity2":{
          "vx":63,
          "vy":173
        }
      },
      {
        "x":159,
        "y":138,
        "rotation":0.0,
        "handleLink":false,
        "velocity2":{
          "vx":-179,
          "vy":184
        }
      }
    ]
  },
  "cameraPath":{
    "mode":"BEZIER_CUBIC",
    "points":[
      {
        "x":705,
        "y":269,
        "rotation":0.0,
        "handleLink":false
      }
    ]
  }
}